{"id":"29e0ef19-d571-47a4-a62b-f174bc12b422","name":"PE with EBacc","code":"2BZ7","qualification":"pgce_with_qts","startDate":"2024-09-01T09:00:00.000Z","applicationsOpenDate":"2023-10-12T00:00:00.000Z","programType":"SD","fundingType":"fee","studyMode":"F","ageRange":"11_to_16","subjectLevel":"secondary","isSend":"no","subjects":[{"id":"74d64a54-5e34-4590-b6c7-528dd0cf26fe","code":"C6","name":"Physical education"}],"locations":[{"id":"d7fc56e3-743d-48ae-be3e-f7d12f5b76ef","name":"Sidney Stringer Academy","isPublished":"N","status":"N","vacancies":"F"}],"trainingProvider":{"id":"c22a7b3a-cd32-4364-a7f8-f95ce2f386a8","code":"18K","name":"Sidney Stringer Academy"},"accreditedBody":{"id":"cf53a0d4-4e3d-43e1-909e-999bc42a4bbf","code":"2A7","name":"The Coventry SCITT"},"profPost":"PG","english":"3","maths":"3","acceptPendingGcse":"no","acceptGcseEquivalency":"no","acceptEnglishGcseEquivalency":"no","acceptMathsGcseEquivalency":"no","courseLength":"OneYear","feesUK":9250,"aboutCourse":"Find out more at:\r\n(http://www.coventryscitt.org.uk/)\r\n","interviewProcess":"Due to COVID restrictions we are currently unable to observe anyone teach within our schools and so have changed our interview process as follows.\r\n\r\nID and qualifications check\r\nObservational task; watching a short video and answering a few questions – 20 mins\r\nLiteracy task; Correcting a piece of text and answering a few questions – 30 mins\r\nOral presentation; stating three reasons what influenced you to become a teacher – 10 mins\r\nFormal Interview;  – 30 mins\r\n","howSchoolPlacementsWork":"Trainees are involved in the decision making process when choosing a main placement school. We endeavour to place trainees in one of their first three choices of schools. The Coventry SCITT organises your second placement for you to ensure you have the opportunity to teach in a contextually different school.\r\n\r\n\r\n","personalQualities":"","otherRequirements":"","status":2,"createdAt":"2021-07-12T13:49:29.665Z","canSponsorStudentVisa":"no","cycle":"2024"}
