{"id":"381aced8-6a9a-4e44-a96d-d4f24226cd1e","name":"Arbor Academy Trust","code":"2EE","type":"lead_school","isAccreditedBody":false,"urn":"143384","ukprn":"10057692","address":{"addressLine1":"Davies Lane","addressLine2":"Leytonstone","town":"London","postcode":"E11 3DR"},"contact":{"website":"http://www.davieslaneteachingschool.co.uk","email":"office@davieslane.arboracademytrust.co.uk","telephone":"2085392466","fullName":"Jason Cook"},"location":{"latitude":51.5638336,"longitude":0.0135604},"trainWithUs":"Davies Lane Primary School has successfully trained trainees. Our aim throughout the course is to ensure that your training needs are met to ensure the best standards of teaching and learning are promoted. You will be training with outstanding practitioners in outstanding schools.","trainWithDisability":"Most schools and external HEI providers have disability access and provide support for trainees with disabilities.","showSchoolPlacements":"no","visaSponsorship":{"canSponsorSkilledWorkerVisa":"no","canSponsorStudentVisa":"no"},"accreditedBodies":[],"createdAt":"2021-07-06T17:53:58.361Z","updatedAt":"2021-11-04T16:40:06.036Z"}
