{"id":"f672fd05-3854-44c2-a3e3-ea3aa0fdb8ad","name":"Primary 5-11","code":"J877","qualification":"pgce_with_qts","startDate":"2023-09-01T09:00:00.000Z","applicationsOpenDate":"2022-10-12T00:00:00.000Z","programType":"SD","fundingType":"fee","studyMode":"F","ageRange":"5_to_11","subjectLevel":"primary","isSend":"no","subjects":[{"id":"32a27d4b-8216-4498-9e7c-ddfba0a38a00","code":"00","name":"Primary"}],"locations":[{"id":"14fd3a5c-4c80-4594-b055-9b0a7a8cf487","name":"Wycliffe CofE Primary School","isPublished":"Y","status":"R","vacancies":"F"},{"id":"8828608f-1d20-4f12-8686-1800a1962f32","name":"St Philip's CofE Primary School","isPublished":"Y","status":"R","vacancies":"F"},{"id":"96b97174-44f1-416f-bccb-add4bbe127c6","name":"St. John's CofE Primary School","isPublished":"Y","status":"R","vacancies":"F"},{"id":"475af89a-775c-4e4f-b98f-73bed5b65538","name":"Oxenhope CofE Primary School","isPublished":"Y","status":"R","vacancies":"F"}],"trainingProvider":{"id":"f43bf51b-2b8b-4272-857e-12a9c389d3f2","code":"3G1","name":"BDAT ITT in partnership with Gorse SCITT"},"accreditedBody":{"id":"59579b9d-79e3-4ab9-a34e-6d11aad8263e","code":"1N1","name":"Gorse SCITT"},"profPost":"PG","degreeGrade":"2","acceptPendingGcse":"yes","acceptGcseEquivalency":"yes","acceptEnglishGcseEquivalency":"yes","acceptMathsGcseEquivalency":"yes","additionalGcseEquivalencies":"We accept equivalencies passed prior to the programme commencing through equivalencytesting.com","courseLength":"OneYear","feesUK":9250,"feesInternational":9250,"aboutCourse":"Our Primary 5-11 programme will develop your skills in teaching outstanding lessons for Primary school pupils. We will use our Subject Knowledge Development programme to ensure that you have all the necessary skills to plan and deliver the Early Years Framework in the Early Years Foundation Stage (EYFS) and the National Curriculum in Key Stage One and Key Stage Two. During your placements, you will develop your pedagogy and practice through working alongside highly experienced school colleagues who have taught successfully in Primary schools for many years. In addition to being placed in two contrasting Primary schools, we also provide you with experience in a Secondary school in order to give you a deeper understanding of what you are building the pupils towards. Throughout the programme, you will work closely with your Professional Mentor, Mentor and Subject Lead to ensure that you get all the support you need to become an excellent teacher.\r\n\r\nAssessment for Qualified Teacher Status will be against our curriculum, the Core Content Framework, and ultimately, the Teachers’ Standards.  You will submit weekly evidence that demonstrates your progress in the classroom, as well as reflections on your training.  You will also receive regular and supportive feedback on your teaching from experienced colleagues.  For the PGCE element, which runs seamlessly alongside your school-based practice, you will complete two research-based university assignments; guidance and support for both QTS and PGCE will be offered throughout the year. ","interviewProcess":"Our interview process is currently offered online. We are also be able to offer a school experience to applicants by negotiation.\r\n\r\nYou will usually be interviewed by a senior tutor from GORSE SCITT, a Senior Leader from a BDAT school, and / or a senior member of the central BDAT ITT team.\r\n\r\n* You will make a short 3-5 minute presentation about why you want to teach and what you will bring to teaching; you should engage with the panel or pupils making clear why you want to be a teacher. \r\n* You will participate in a lesson with a fully qualified teacher, interacting with students, helping them, answering questions and assisting the teacher with the lesson.\r\n*You will have a formal interview which will give you the opportunity to discuss why you want to be a teacher, what you would bring to the profession, and also show us your resilience and initiative.\r\n* You will be asked to complete a range of written work. These will include subjects such as current issues facing education, reasons for your subject being part of the curriculum, your desire to teach, the importance of safeguarding, and subject knowledge questions.\r\n* After your interview, we aim to let you know if you have been successful within 48 hours.\r\n\r\nIf we regard you as a strong candidate who needs further development to be ready to join our programme we will facilitate this through our Subject Knowledge Enhancement programmes.\r\n","howSchoolPlacementsWork":"All of our Trust schools are detailed on our website.  We have worked hard to ensure that you will complete a minimum of two contrasting placements, each designed and personalised so that you will make real progress during the year.  \r\n\r\nYou will not be offered a place on our programme if we do not have a quality placement experience to offer you.  We will organise and make all your placement arrangements for you.  In addition to your placements, your central and subject training will focus on what excellent classroom practice looks like, whilst always ensuring that you are aware of what effective and relevant evidenced-based practice looks like.   \r\n\r\nYou will be taught how to take a reflective and analytical view of your teaching and know how to make effective progress.  You will work alongside, and be mentored by, a range of expert and experienced colleagues – Subject Leads, Professional Mentors, Placement Mentors and the ITT team – who will all ensure that by the end of your training you are able to teach in any setting, in any context and in any location.\r\n\r\nYou will experience and teach across two key stages. For Primary that will be Key Stages One and Two (ages 4 to 11). \r\n\r\nYou will have a minimum of two placements, one from September to Christmas and one from January to June. A third placement maybe offered as applicable and if in your best interests.\r\n\r\nYou will usually be in school three days and two mornings every week and expected to follow the timings, practices and culture of the school.\r\n\r\nWe believe that all trainees, morally, should understand where pupils have been on their educational journey so far, and where their journey may take them.  As such, all trainees will experience teaching enhancements from Early Years to Year 13 and beyond.  \r\n","personalQualities":"Has high moral purpose in their desire to become a teacher.\r\nIs able to respond positively to guidance towards self-improvement.\r\nHas an intrinsic passion for learning.\r\nIs fully prepared and demonstrates a clear understanding of teaching in a socially and culturally diverse society.\r\n\r\nAssumes a high level of responsibility for the well-being, attainment, progress and outcomes of pupils.\r\n\r\nPlans lessons that use appropriate, imaginative and creative strategies that match the individual learning styles and needs of pupils.\r\n\r\nDemonstrates excellent subject knowledge and is able to apply this and the appropriate learning and teaching pedagogy to support the pupils they teach.\r\n","otherRequirements":"Offers will be subject to an Enhanced DBS which will be organised for you. We encourage you to enrol to the DBS update service. An overseas DBS may be required for those who have spent time outside of the UK.\r\n\r\nAll applicants will be required to complete proficiency tests in English and Mathematics which will be delivered by BDAT ITT in partnership with Gorse SCITT.\r\n","status":1,"createdAt":"2021-10-06T08:42:23.926Z","updatedAt":"2021-10-06T08:43:49.230Z","canSponsorStudentVisa":"no","cycle":"2024"}
