{"id":"01b66921-40d6-4c3e-83be-3fb7a7fe19a0","firstName":"Korbin","lastName":"Stanton","email":"korbin.stanton-9281@example.com","username":"korbin.stanton-9281@example.com","password":"bat","organisations":[{"id":"f652c4be-0c09-4451-9aa3-8cd5b850ca70","code":"1NC","name":"Sola Fide Multi-Academy Trust","permissions":[],"notifications":["course_published","course_changed","course_withdrawn","course_vacancies_changed"]}],"createdAt":"2022-03-07T12:32:35.566Z","updatedAt":"2022-03-08T20:09:43.853Z","active":false}