{"id":"06d2a4a5-81a3-4e89-b19c-3ef2851767f9","firstName":"Austen","lastName":"Schroeder","email":"austen.schroeder-10741@example.com","username":"austen.schroeder-10741@example.com","password":"bat","organisations":[{"id":"111dd349-9bea-46b6-b75c-e13581145b55","code":"27Q","name":"Wigan and West Lancashire Catholic School Direct","permissions":[],"notifications":["course_published","course_changed","course_withdrawn","course_vacancies_changed"]}],"createdAt":"2022-03-07T12:34:29.171Z","updatedAt":"2022-03-08T20:09:44.269Z","active":true}