{"id":"09f78bb4-171d-4d56-88c1-60c38d351dc2","firstName":"Earline","lastName":"Greenholt","email":"earline.greenholt-8054@example.com","username":"earline.greenholt-8054@example.com","password":"bat","organisations":[{"id":"82fd3a3b-6bfd-40d1-8343-0c19e34a847a","code":"T92","name":"2Schools Consortium","permissions":[],"notifications":["course_published","course_changed","course_withdrawn","course_vacancies_changed","course_published_training_provider","course_changed_training_provider","course_withdrawn_training_provider","course_vacancies_changed_training_provider"]},{"id":"010f4997-79c0-45f4-9e74-6ba418c0d2a5","code":"151","name":"Oakthorpe Primary School","permissions":[],"notifications":["course_published","course_changed","course_withdrawn","course_vacancies_changed"]}],"createdAt":"2022-03-07T12:31:08.878Z","updatedAt":"2022-03-08T20:09:43.317Z","active":false}