{"id":"1159c3b8-7bdf-4624-bb5b-fbcb80f6ce7e","firstName":"Claud","lastName":"Hayes","email":"claud.hayes-10067@example.com","username":"claud.hayes-10067@example.com","password":"bat","organisations":[{"id":"bf3e7945-a19a-4d47-9f51-1df9f5dc5d05","code":"1QL","name":"Geoffrey Field Junior School","permissions":[],"notifications":["course_published","course_changed","course_withdrawn","course_vacancies_changed"]}],"createdAt":"2022-03-07T12:33:35.070Z","updatedAt":"2022-03-08T20:09:44.083Z","active":false}