{"id":"158f2ad0-b6a0-4579-9bc8-ae697ae337cb","firstName":"Thaddeus","lastName":"Runolfsdottir","email":"thaddeus.runolfsdottir-11805@example.com","username":"thaddeus.runolfsdottir-11805@example.com","password":"bat","organisations":[{"id":"b078ae49-5184-4104-9a4f-b61bd5a591be","code":"28A","name":"Devon Moorland Schools Partnership","permissions":[],"notifications":["course_published","course_changed","course_withdrawn","course_vacancies_changed"]},{"id":"88e5549a-3fc5-4d67-8eec-eb68ea17a2ed","code":"1T7","name":"Plymouth Teachers and Schools Alliance","permissions":[],"notifications":["course_published","course_changed","course_withdrawn","course_vacancies_changed"]}],"createdAt":"2022-03-07T12:36:02.071Z","updatedAt":"2022-03-08T20:09:44.869Z","active":false}