{"id":"2b553089-a7a3-4c8f-9fcd-0b8eed3ea41e","firstName":"Fannie","lastName":"Cartwright","email":"fannie.cartwright-10096@example.com","username":"fannie.cartwright-10096@example.com","password":"bat","organisations":[{"id":"222a5fbc-f990-4836-bddb-69c8ff0e41dc","code":"29P","name":"St Bernard’s School Direct Training","permissions":[],"notifications":["course_published","course_changed","course_withdrawn","course_vacancies_changed"]}],"createdAt":"2022-03-07T12:33:37.020Z","updatedAt":"2022-03-08T20:09:44.090Z","active":false}