{"id":"3b74110c-3f2d-46d2-ac01-fa754a6ddf4d","firstName":"Deshawn","lastName":"Kohler","email":"deshawn.kohler-10698@example.com","username":"deshawn.kohler-10698@example.com","password":"bat","organisations":[{"id":"3d2272b0-97ac-4128-873b-13e3ebaec6c3","code":"5J7","name":"Redwell Primary School","permissions":[],"notifications":["course_published","course_changed","course_withdrawn","course_vacancies_changed"]}],"createdAt":"2022-03-07T12:34:23.948Z","updatedAt":"2022-03-08T20:09:44.245Z","active":false}