{"id":"4011e51d-f675-4db8-81dd-fafab7ef71d0","firstName":"Raphaelle","lastName":"Tillman","email":"raphaelle.tillman-11368@example.com","username":"raphaelle.tillman-11368@example.com","password":"bat","organisations":[{"id":"4f5080d8-c453-48d4-87b7-0bac79dce8ec","code":"1QK","name":"The Denbigh Alliance","permissions":[],"notifications":["course_published","course_changed","course_withdrawn","course_vacancies_changed"]},{"id":"eb4a38dd-1429-4c88-b2ee-a552369e4306","code":"1YK","name":"The Tommy Flowers SCITT Milton Keynes","permissions":[],"notifications":["course_published","course_changed","course_withdrawn","course_vacancies_changed","course_published_training_provider","course_changed_training_provider","course_withdrawn_training_provider","course_vacancies_changed_training_provider"]}],"createdAt":"2022-03-07T12:35:25.773Z","updatedAt":"2022-03-08T20:09:44.705Z","active":true}