{"id":"55551b07-2747-45b5-a922-f97a2f7f4bb3","firstName":"Hazel","lastName":"Schneider","email":"hazel.schneider-9294@example.com","username":"hazel.schneider-9294@example.com","password":"bat","organisations":[{"id":"d0d173a3-514d-418a-9fbd-b48d98a5bdef","code":"1BD","name":"AIM Primary Alliance","permissions":[],"notifications":["course_published","course_changed","course_withdrawn","course_vacancies_changed"]}],"createdAt":"2022-03-07T12:32:36.386Z","updatedAt":"2022-03-08T20:09:43.857Z","active":true}