{"id":"5c4a0874-0e5c-4622-a921-62fd1958e1e5","firstName":"Maida","lastName":"Kilback","email":"maida.kilback-11529@example.com","username":"maida.kilback-11529@example.com","password":"bat","organisations":[{"id":"294d0e65-0b96-46d1-a8eb-f27c9a96d9d2","code":"1JS","name":"Teach Cheshire","permissions":[],"notifications":["course_published","course_changed","course_withdrawn","course_vacancies_changed"]}],"createdAt":"2022-03-07T12:35:38.757Z","updatedAt":"2022-03-08T20:09:44.760Z","active":true}