{"id":"6180870e-4d5c-45ac-a556-d5d778e4ba14","firstName":"Renee","lastName":"Cruickshank","email":"renee.cruickshank-10103@example.com","username":"renee.cruickshank-10103@example.com","password":"bat","organisations":[{"id":"7cb26c78-f71a-4cfb-8823-f8a8c2eff488","code":"1A2","name":"Oasis Innovation","permissions":[],"notifications":["course_published","course_changed","course_withdrawn","course_vacancies_changed"]}],"createdAt":"2022-03-07T12:33:37.455Z","updatedAt":"2022-03-08T20:09:44.092Z","active":false}