{"id":"a36105d7-e90e-4672-9d99-e255f0424651","firstName":"Bette","lastName":"Hirthe","email":"bette.hirthe-9780@example.com","username":"bette.hirthe-9780@example.com","password":"bat","organisations":[{"id":"e806d5d7-c3fc-45cd-b5b3-f3b9b9ffaa91","code":"23R","name":"Windsor Teaching Alliance","permissions":[],"notifications":["course_published","course_changed","course_withdrawn","course_vacancies_changed"]}],"createdAt":"2022-03-07T12:33:07.445Z","updatedAt":"2022-03-08T20:09:43.992Z","active":false}