{"id":"a6cc5d98-e926-4bb5-bd74-a463b4aadb15","firstName":"Shanelle","lastName":"Anderson","email":"shanelle.anderson-10737@example.com","username":"shanelle.anderson-10737@example.com","password":"bat","organisations":[{"id":"12d161ca-40a3-4224-a1ec-95ba1781e61f","code":"2KN","name":"St Mary’s Catholic School","permissions":[],"notifications":["course_published","course_changed","course_withdrawn","course_vacancies_changed"]}],"createdAt":"2022-03-07T12:34:28.864Z","updatedAt":"2022-03-08T20:09:44.267Z","active":true}