{"id":"c5446514-f1a6-4af6-bd29-5d5e6c85d2ce","firstName":"Celia","lastName":"Schmitt","email":"celia.schmitt-9572@example.com","username":"celia.schmitt-9572@example.com","password":"bat","organisations":[{"id":"43670709-fc69-4edf-8f5a-e6ed6d4386a9","code":"1Y1","name":"Maiden Erlegh Institute","permissions":[],"notifications":["course_published","course_changed","course_withdrawn","course_vacancies_changed"]}],"createdAt":"2022-03-07T12:32:53.527Z","updatedAt":"2022-03-08T20:09:43.941Z","active":false}