{"id":"d2c8cc08-7ee2-4726-8064-29e582770cf4","firstName":"Randall","lastName":"Mitchell","email":"randall.mitchell-8637@example.com","username":"randall.mitchell-8637@example.com","password":"bat","organisations":[{"id":"a58030f9-9701-4856-859f-feca6405ddd6","code":"2E4","name":"St Stephen’s CofE Primary School","permissions":[],"notifications":["course_published","course_changed","course_withdrawn","course_vacancies_changed"]}],"createdAt":"2022-03-07T12:31:51.271Z","updatedAt":"2022-03-08T20:09:43.619Z","active":true}