{"id":"61258399-5225-47dd-8dc5-32ab7a8e8ff7","name":"Outwood Academy Freeston","urn":145937,"code":"7","address":{"addressLine1":"Favell Avenue","addressLine2":"Normanton","town":"Wakefield","county":"West Yorkshire","postcode":"WF6 1HZ","regionCode":9},"location":{"latitude":53.6953587,"longitude":-1.41241},"organisation":{"id":"c4672112-c1c3-47fe-b197-dcd2b002a852","name":"NIoT@Outwood Grange Academies Trust","code":"1GV"},"createdAt":"2022-07-06T11:05:28.820Z","updatedAt":"2022-07-06T11:05:28.820Z"}